setup.py
reticul8/__init__.py
reticul8/arduino.py
reticul8/block_compressor.py
reticul8/nanopb_pb2.py
reticul8/pjon_strategies.py
reticul8/plugin_pb2.py
reticul8/reticul8_pb2.py
reticul8/rpc.py
reticul8.egg-info/PKG-INFO
reticul8.egg-info/SOURCES.txt
reticul8.egg-info/dependency_links.txt
reticul8.egg-info/top_level.txt