Metadata-Version: 2.1
Name: reticul8
Version: 0.1
Summary: What do you get if you combine Python and and MCUs?
Home-page: https://github.com/xlfe/reticul8
Author: xlfe
License: Apache 2.0
Platform: UNKNOWN
Classifier: Programming Language :: Python :: 3.5
Classifier: Programming Language :: Python :: 3.6
Classifier: Programming Language :: Python :: 3.7
